{
  "races": [
    {
      "id": "2txtk71oi4aobtg",
      "name": "Maratona da Cidade",
      "date": "2026-04-15",
      "description": "Uma maratona completa de 42.2km atraves das ruas vibrantes da cidade. Perfeita para corredores experientes que buscam um desafio epico.",
      "distance": 42.2,
      "featured": true,
      "imageUrl": "",
      "location": "Sao Paulo, SP",
      "organizerId": "organizer-default",
      "price": 89.99,
      "status": "published",
      "time": "05:30",
      "created": null,
      "updated": null
    },
    {
      "id": "fy9o0l4sl1bsosx",
      "name": "Corrida Divertida 5K",
      "date": "2026-04-22",
      "description": "Uma corrida casual de 5km ideal para iniciantes e familias. Divirta-se enquanto se exercita em um ambiente acolhedor.",
      "distance": 5,
      "featured": true,
      "imageUrl": "",
      "location": "Rio de Janeiro, RJ",
      "organizerId": "organizer-default",
      "price": 29.99,
      "status": "published",
      "time": "07:00",
      "created": null,
      "updated": null
    },
    {
      "id": "1ajy4p5g5d92oez",
      "name": "Corrida de Trilha 10K",
      "date": "2026-05-10",
      "description": "Desafio de 10km em trilhas naturais com paisagens deslumbrantes. Recomendado para corredores com experiencia em terrenos variados.",
      "distance": 10,
      "featured": true,
      "imageUrl": "",
      "location": "Belo Horizonte, MG",
      "organizerId": "organizer-default",
      "price": 49.99,
      "status": "published",
      "time": "06:15",
      "created": null,
      "updated": null
    },
    {
      "id": "ewr6sosw1f5crue",
      "name": "Meia Maratona",
      "date": "2026-05-18",
      "description": "Uma meia maratona de 21.1km para corredores intermediarios. Teste sua resistencia em um percurso bem organizado.",
      "distance": 21.1,
      "featured": false,
      "imageUrl": "",
      "location": "Brasilia, DF",
      "organizerId": "organizer-default",
      "price": 59.99,
      "status": "published",
      "time": "05:45",
      "created": null,
      "updated": null
    },
    {
      "id": "bd38rc5bepi7auy",
      "name": "Corrida Sprint",
      "date": "2026-05-30",
      "description": "Uma corrida rapida de 3km perfeita para quem quer comecar. Otima para melhorar sua velocidade e resistencia.",
      "distance": 3,
      "featured": false,
      "imageUrl": "",
      "location": "Curitiba, PR",
      "organizerId": "organizer-default",
      "price": 19.99,
      "status": "published",
      "time": "08:00",
      "created": null,
      "updated": null
    },
    {
      "id": "f8ct8txg6nwc39z",
      "name": "City Marathon",
      "date": "2026-06-05",
      "description": "Percurso urbano com altimetria equilibrada para atletas que querem performance e experiencia internacional.",
      "distance": 42.2,
      "featured": false,
      "imageUrl": "",
      "location": "Downtown",
      "organizerId": "organizer-default",
      "price": 89,
      "status": "published",
      "time": "06:00",
      "created": null,
      "updated": null
    },
    {
      "id": "9nuur3msbwg4a4s",
      "name": "Spring 5K",
      "date": "2026-06-12",
      "description": "Prova leve e colorida pensada para iniciantes, assessorias e publico corporativo.",
      "distance": 5,
      "featured": false,
      "imageUrl": "",
      "location": "Central Park",
      "organizerId": "organizer-default",
      "price": 25,
      "status": "published",
      "time": "07:30",
      "created": null,
      "updated": null
    },
    {
      "id": "af0ojzcz2bu6xwc",
      "name": "Mountain Trail Run",
      "date": "2026-06-19",
      "description": "Trilhas tecnicas e vistas amplas para atletas que buscam aventura e contato com a natureza.",
      "distance": 15,
      "featured": false,
      "imageUrl": "",
      "location": "Mountain Ridge",
      "organizerId": "organizer-default",
      "price": 45,
      "status": "published",
      "time": "06:40",
      "created": null,
      "updated": null
    },
    {
      "id": "30i6crjv5xoex08",
      "name": "Half Marathon Challenge",
      "date": "2026-06-26",
      "description": "Evento desenhado para quem quer buscar recorde pessoal em um circuito rapido e seguro.",
      "distance": 21.1,
      "featured": false,
      "imageUrl": "",
      "location": "Riverside",
      "organizerId": "organizer-default",
      "price": 65,
      "status": "published",
      "time": "05:50",
      "created": null,
      "updated": null
    },
    {
      "id": "f3gxztqb7jsaker",
      "name": "Urban 10K",
      "date": "2026-07-03",
      "description": "Corrida de 10km para atletas que gostam de cidade, ritmo forte e estrutura premium.",
      "distance": 10,
      "featured": false,
      "imageUrl": "",
      "location": "City Streets",
      "organizerId": "organizer-default",
      "price": 35,
      "status": "draft",
      "time": "07:10",
      "created": null,
      "updated": null
    }
  ],
  "organizers": [
    {
      "id": "organizer-default",
      "name": "Equipe RunTrack",
      "email": "organizer@runtrack.local",
      "password": "runtrack123"
    }
  ],
  "organizerSessions": [
    {
      "token": "00e08bcf-9ba9-4d7b-ab13-f59c64988a11",
      "organizerId": "organizer-default",
      "created": "2026-03-30T11:02:35.118Z"
    }
  ],
  "athletes": [
    {
      "id": "1e571744-7e80-4afb-a96d-004666a78ab5",
      "name": "loanny santos",
      "email": "loannysantos@gmail.com",
      "password": "123",
      "created": "2026-03-29T17:08:37.944Z"
    }
  ],
  "athleteSessions": [
    {
      "token": "3e528d07-835b-43ca-bb31-fbe3927ed3bc",
      "athleteId": "1e571744-7e80-4afb-a96d-004666a78ab5",
      "created": "2026-03-29T17:38:33.179Z"
    }
  ],
  "coupons": [],
  "registrations": [
    {
      "fullName": "Nescau Play Macabro",
      "email": "samuellivethim101@gmail.com",
      "phone": "71999942727",
      "dateOfBirth": "1997-02-15",
      "tShirtSize": "S",
      "emergencyContactName": "SAMUEL FAGUNDES SANTOS",
      "emergencyContactPhone": "71999942727",
      "id": "187e1297-4d65-4e2c-a20a-4692e034643d",
      "created": "2026-03-29T18:52:37.239Z",
      "confirmationNumber": "RUN10357239",
      "ownerId": "50d30cea-c3ee-4093-b177-3ee4725ffad9",
      "athleteId": null,
      "status": "pending_payment",
      "raceId": "fy9o0l4sl1bsosx",
      "raceName": "Corrida Divertida 5K",
      "racePrice": 29.99,
      "couponCode": null,
      "couponRedeemedAt": null,
      "discountAmount": 0,
      "finalPrice": 29.99,
      "paymentStatus": "pending",
      "paymentMethod": null,
      "paymentProvider": "simulated",
      "paymentCheckoutUrl": null,
      "paymentPreferenceId": null,
      "paymentOrderId": null,
      "paymentExternalReference": null,
      "paymentStatusDetail": null,
      "paymentPayer": null,
      "paymentQrCode": null,
      "paymentQrCodeBase64": null,
      "paymentTicketUrl": null,
      "paymentDigitableLine": null,
      "paymentBarcodeContent": null,
      "paymentExpiresAt": null,
      "paidAt": null,
      "kitStatus": "separated",
      "checkInStatus": "pending",
      "checkInAt": null
    },
    {
      "fullName": "SAMUEL FAGUNDES SANTOS",
      "email": "samuellivethim101@gmail.com",
      "phone": "71999942727",
      "dateOfBirth": "1995-12-15",
      "tShirtSize": "S",
      "emergencyContactName": "SAMUEL FAGUNDES SANTOS",
      "emergencyContactPhone": "71999942727",
      "id": "00beeabb-5bad-457e-90c1-f144d5d0daad",
      "created": "2026-03-29T18:47:38.554Z",
      "confirmationNumber": "RUN10058554",
      "ownerId": "50d30cea-c3ee-4093-b177-3ee4725ffad9",
      "athleteId": null,
      "status": "pending_payment",
      "raceId": "bd38rc5bepi7auy",
      "raceName": "Corrida Sprint",
      "racePrice": 19.99,
      "couponCode": null,
      "couponRedeemedAt": null,
      "discountAmount": 0,
      "finalPrice": 19.99,
      "paymentStatus": "pending",
      "paymentMethod": null,
      "paymentProvider": "simulated",
      "paymentCheckoutUrl": null,
      "paymentPreferenceId": null,
      "paymentOrderId": null,
      "paymentExternalReference": null,
      "paymentStatusDetail": null,
      "paymentPayer": null,
      "paymentQrCode": null,
      "paymentQrCodeBase64": null,
      "paymentTicketUrl": null,
      "paymentDigitableLine": null,
      "paymentBarcodeContent": null,
      "paymentExpiresAt": null,
      "paidAt": null,
      "kitStatus": "pending",
      "checkInStatus": "pending",
      "checkInAt": null
    },
    {
      "fullName": "loanny santos",
      "email": "loannysantos@gmail.com",
      "phone": "71999942727",
      "dateOfBirth": "1995-12-15",
      "tShirtSize": "M",
      "emergencyContactName": "SAMUEL FAGUNDES SANTOS",
      "emergencyContactPhone": "71999942727",
      "id": "a02a860c-c6ee-4696-8c8b-be77bc603576",
      "created": "2026-03-29T17:43:38.213Z",
      "confirmationNumber": "RUN06218213",
      "ownerId": null,
      "athleteId": "1e571744-7e80-4afb-a96d-004666a78ab5",
      "status": "pending_payment",
      "raceId": "fy9o0l4sl1bsosx",
      "raceName": "Corrida Divertida 5K",
      "racePrice": 29.99,
      "couponCode": null,
      "couponRedeemedAt": null,
      "discountAmount": 0,
      "finalPrice": 29.99,
      "paymentStatus": "pending",
      "paymentMethod": null,
      "paymentProvider": "simulated",
      "paymentCheckoutUrl": null,
      "paymentPreferenceId": null,
      "paymentOrderId": null,
      "paymentExternalReference": null,
      "paymentStatusDetail": null,
      "paymentPayer": null,
      "paymentQrCode": null,
      "paymentQrCodeBase64": null,
      "paymentTicketUrl": null,
      "paymentDigitableLine": null,
      "paymentBarcodeContent": null,
      "paymentExpiresAt": null,
      "paidAt": null,
      "kitStatus": "pending",
      "checkInStatus": "checked_in",
      "checkInAt": "2026-03-29T18:31:17.346Z"
    }
  ],
  "contactLeads": [],
  "emailQueue": [
    {
      "id": "d098c317-133b-4756-bc21-9d9f7b217dd3",
      "created": "2026-03-29T18:52:37.239Z",
      "status": "sent",
      "kind": "registration_received",
      "to": "samuellivethim101@gmail.com",
      "subject": "Reserva recebida para Corrida Divertida 5K",
      "preview": "Sua reserva foi criada. Finalize o pagamento para confirmar a inscricao no evento.",
      "relatedRegistrationId": "187e1297-4d65-4e2c-a20a-4692e034643d",
      "relatedLeadId": null,
      "sentAt": "2026-03-29T20:09:02.404Z",
      "providerMessageId": null
    },
    {
      "id": "d88e4003-a7ee-41bf-8c61-c2a8065432e1",
      "created": "2026-03-29T18:47:38.556Z",
      "status": "sent",
      "kind": "registration_received",
      "to": "samuellivethim101@gmail.com",
      "subject": "Reserva recebida para Corrida Sprint",
      "preview": "Sua reserva foi criada. Finalize o pagamento para confirmar a inscricao no evento.",
      "relatedRegistrationId": "00beeabb-5bad-457e-90c1-f144d5d0daad",
      "relatedLeadId": null,
      "sentAt": "2026-03-29T20:09:02.406Z",
      "providerMessageId": null
    },
    {
      "id": "86fe6d27-36ec-40b3-ade5-29ce0b7ab760",
      "created": "2026-03-29T17:43:38.213Z",
      "status": "sent",
      "kind": "registration_received",
      "to": "loannysantos@gmail.com",
      "subject": "Reserva recebida para Corrida Divertida 5K",
      "preview": "Sua reserva foi criada. Finalize o pagamento para confirmar a inscricao no evento.",
      "relatedRegistrationId": "a02a860c-c6ee-4696-8c8b-be77bc603576",
      "relatedLeadId": null,
      "sentAt": "2026-03-29T20:09:02.406Z",
      "providerMessageId": null
    }
  ]
}